pydocparse/__init__.py
pydocparse/docstring.py
pydocparse-0.0.1.dist-info/LICENSE.txt
pydocparse-0.0.1.dist-info/METADATA
pydocparse-0.0.1.dist-info/WHEEL
pydocparse-0.0.1.dist-info/top_level.txt
pydocparse-0.0.1.dist-info/RECORD
